pipeline_sdk_test40/__init__.py
pipeline_sdk_test40/auth_service.py
pipeline_sdk_test40/inference_pipeline.py
pipeline_sdk_test40/model_inference_dsl_component.py
pipeline_sdk_test40/model_train_dsl_component.py
pipeline_sdk_test40/model_validate_dsl_component.py
pipeline_sdk_test40/pipeline_util.py
pipeline_sdk_test40/run_inference_pipeline.py
pipeline_sdk_test40/run_training_pipeline.py
pipeline_sdk_test40/run_validate_pipeline.py
pipeline_sdk_test40/train_pipeline.py
pipeline_sdk_test40/validate_pipeline.py
pipeline_sdk_test40-1.0.0.dist-info/METADATA
pipeline_sdk_test40-1.0.0.dist-info/WHEEL
pipeline_sdk_test40-1.0.0.dist-info/top_level.txt
pipeline_sdk_test40-1.0.0.dist-info/RECORD
